{
  "$schema": "https://mintlify.com/schema.json",
  "name": "DigitalForce Documentation",
  "logo": {
    "dark": "/logo/digitalforce-light.png",
    "light": "/logo/digitalforce-dark.png"
  },
  "favicon": "/favicon-32x32.png",
  "colors": {
    "primary": "#9860ff",
    "light": "#9860ff",
    "dark": "#9860ff",
    "anchors": {
      "from": "#9860ff",
      "to": "#9860ff"
    }
  },
  "topbarLinks": [
    {
      "name": "Support",
      "url": "mailto:support-digitalforce@allaboutai.com"
    }
  ],
  "topbarCtaButton": {
    "name": "Product Hunt",
    "url": "https://www.producthunt.com/posts/kiva-3"
  },
  "anchors": [
    {
      "name": "Community",
      "icon": "discord",
      "url": "https://discord.gg/digitalforce"
    },
    {
      "name": "Blog",
      "icon": "newspaper",
      "url": "https://digitalforce.ai/blog"
    }
  ],
  "navigation": [
    {
      "group": "Getting Started",
      "pages": [
        "introduction",
        "get-started"
      ]
    },
  ],
  "footerSocials": {
    "twitter": "https://twitter.com/digitalforce",
    "github": "https://github.com/digitalforce",
    "linkedin": "https://linkedin.com/company/digitalforce"
  }
} 
